[
  {
    "nombre": "Libertad",
    "partido": "Almirante Brown",
    "poblacion": 1249,
    "horages": 351,
    "viviendas": 348,
    "superficie": 11.21,
    "densidad": 111,
    "link": "https://drive.google.com/file/d/1FbV7d0q-QCWakk221TT3Td-6yeg8CmOj/view?usp=sharing"
  },
  {
    "nombre": "Don Orione Viejo",
    "partido": "Almirante Brown",
    "poblacion": 3594,
    "hogares": 1048,
    "viviendas": 1040,
    "superficie": 25.53,
    "densidad": 141,
    "link": "https://drive.google.com/file/d/1FbV7d0q-QCWakk221TT3Td-6yeg8CmOj/view?usp=sharing"
  }
]


<tr>
<th>
<blockquote style="color: #FFFFFF;">6 de Diciembre</p>
</th>
<th>
<blockquote style="color: #FFFFFF;">Almirante Brown</p>
</th>
<th>
<blockquote style="color: #FFFFFF;">465</p>
</th>
<th>
<blockquote style="color: #FFFFFF;">102</p>
</th>
<th>
<blockquote style="color: #FFFFFF;">144</p>
</th>
<th>
<blockquote style="color: #FFFFFF;">3,61</p>
</th>
<th>
<blockquote style="color: #FFFFFF;">129</p>
</th>

</tr>
<th>
<blockquote style="color: #FFFFFF;">Inflamable</p>
</th>
<th>
<blockquote style="color: #FFFFFF;">Avellaneda</p>
</th>
<th>
<blockquote style="color: #FFFFFF;">3761</p>
</th>
<th>
<blockquote style="color: #FFFFFF;">1083</p>
</th>
<th>
<blockquote style="color: #FFFFFF;">810</p>
</th>
<th>
<blockquote style="color: #FFFFFF;">40,85</p>
</th>
<th>
<blockquote style="color: #FFFFFF;">92</p>
</th>
</tr>
<th>
<blockquote style="color: #FFFFFF;">Tranquila</p>
</th>
<th>
<blockquote style="color: #FFFFFF;">Avellaneda</p>
</th>
<th>
<blockquote style="color: #FFFFFF;">7193</p>
</th>
<th>
<blockquote style="color: #FFFFFF;">1991</p>
</th>
<th>
<blockquote style="color: #FFFFFF;">2100</p>
</th>
<th>
<blockquote style="color: #FFFFFF;">39,21</p>
</th>
<th>
<blockquote style="color: #FFFFFF;">183</p>
</th>
</tr>
<th>
<blockquote style="color: #FFFFFF;">Villa Corina</p>
</th>
<th>
<blockquote style="color: #FFFFFF;">Avellaneda</p>
</th>
<th>
<blockquote style="color: #FFFFFF;">9633</p>
</th>
<th>
<blockquote style="color: #FFFFFF;">2615</p>
</th>
<th>
<blockquote style="color: #FFFFFF;">2309</p>
</th>
<th>
<blockquote style="color: #FFFFFF;">58,78</p>
</th>
<th>
<blockquote style="color: #FFFFFF;">164</p>
</th>
</tr>
<tr>
<th>
<a href="https://drive.google.com/file/d/1l7jcXOl7kVOHbonO-5DOfprC1mrYKcCp/view?usp=sharing"
target="_blank" style="color: #FFFFFF;">
<blockquote style="color: #FFFFFF;">Autódromo</p></img>
</a>
</th>
<th>
<blockquote style="color: #FFFFFF;">General Pueyrredón</p>
</th>
<th>
<blockquote style="color: #FFFFFF;">3867</p>
</th>
<th>
<blockquote style="color: #FFFFFF;">982</p>
</th>
<th>
<blockquote style="color: #FFFFFF;">881</p>
</th>
<th>
<blockquote style="color: #FFFFFF;">60,99</p>
</th>
<th>
<blockquote style="color: #FFFFFF;">63</p>
</th>
</tr>
<tr>
<th>
<a href="https://drive.google.com/file/d/1l7jcXOl7kVOHbonO-5DOfprC1mrYKcCp/view?usp=sharing"
target="_blank" style="color: #FFFFFF;">
<blockquote style="color: #FFFFFF;">Nuevo Golf</p></img>
</a>
</th>
<th>
<blockquote style="color: #FFFFFF;">General Pueyrredón</p>
</th>
<th>
<blockquote style="color: #FFFFFF;">2050</p>
</th>
<th>
<blockquote style="color: #FFFFFF;">530</p>
</th>
<th>
<blockquote style="color: #FFFFFF;">567</p>
</th>
<th>
<blockquote style="color: #FFFFFF;">72,08</p>
</th>
<th>
<blockquote style="color: #FFFFFF;">28</p>
</th>
</tr>
<tr>

<th>
<a href="https://drive.google.com/file/d/1TENJhN-iz0FQdiZxLcOBt3ptgWCvftq5/view?usp=sharing"
target="_blank" style="color: #FFFFFF;">
<blockquote style="color: #FFFFFF;">CC8</p></img>
</a>
</th>
<th>
<blockquote style="color: #FFFFFF;">Gral. San Martín</p>
</th>
<th>
<blockquote style="color: #FFFFFF;">18711</p>
</th>
<th>
<blockquote style="color: #FFFFFF;">5072</p>
</th>
<th>
<blockquote style="color: #FFFFFF;">4924</p>
</th>
<th>
<blockquote style="color: #FFFFFF;">74,75</p>
</th>
<th>
<blockquote style="color: #FFFFFF;">250</p>
</th>
</tr>
<tr>
<th>
<a href="https://drive.google.com/file/d/1GWaetXeR_FZnmtT-a2vqE0B6Kzvx6KXn/view?usp=sharing"
target="_blank" style="color: #FFFFFF;">
<blockquote style="color: #FFFFFF;">17 de Marzo </p></img>
</a>
</th>
<th>
<blockquote style="color: #FFFFFF;">La Matanza</p>
</th>
<th>
<blockquote style="color: #FFFFFF;">4125</p>
</th>
<th>
<blockquote style="color: #FFFFFF;">1050</p>
</th>
<th>
<blockquote style="color: #FFFFFF;">917</p>
</th>
<th>
<blockquote style="color: #FFFFFF;">29,78</p>
<th>
<blockquote style="color: #FFFFFF;">138</p>
</th>
</th>
</th>
</tr>
<tr>

<th>
<a href="https://drive.google.com/file/d/1GWaetXeR_FZnmtT-a2vqE0B6Kzvx6KXn/view?usp=sharing"
target="_blank" style="color: #FFFFFF;">
<blockquote style="color: #FFFFFF;">17 de Marzo Bis</p></img>
</a>
</th>
<th>
<blockquote style="color: #FFFFFF;">La Matanza</p>
</th>
<th>
<blockquote style="color: #FFFFFF;">688</p>
</th>
<th>
<blockquote style="color: #FFFFFF;">173</p>
</th>
<th>
<blockquote style="color: #FFFFFF;">165</p>
</th>
<th>
<blockquote style="color: #FFFFFF;">4,95</p>
</th>
<th>
<blockquote style="color: #FFFFFF;">139</p>
</th>
</tr>
<tr>
<th>
<a href="https://drive.google.com/file/d/1GWaetXeR_FZnmtT-a2vqE0B6Kzvx6KXn/view?usp=sharing"
target="_blank" style="color: #FFFFFF;">
<blockquote style="color: #FFFFFF;">Puerta de Hierro</p></img>
</a>
</th>
<th>
<blockquote style="color: #FFFFFF;">La Matanza</p>
</th>
<th>
<blockquote style="color: #FFFFFF;">5316</p>
</th>
<th>
<blockquote style="color: #FFFFFF;">1349</p>
</th>
<th>
<blockquote style="color: #FFFFFF;">1140</p>
</th>
<th>
<blockquote style="color: #FFFFFF;">19,61</p>
</th>
<th>
<blockquote style="color: #FFFFFF;">271</p>
</th>


</tr>
<tr>
<th>
<a href="https://drive.google.com/file/d/1GWaetXeR_FZnmtT-a2vqE0B6Kzvx6KXn/view?usp=sharing"
target="_blank" style="color: #FFFFFF;">
<blockquote style="color: #FFFFFF;">San Petersburgo</p></img>
</a>
</th>
<th>
<blockquote style="color: #FFFFFF;">La Matanza</p>
</th>
<th>
<blockquote style="color: #FFFFFF;">2252</p>
</th>
<th>
<blockquote style="color: #FFFFFF;">544</p>
</th>
<th>
<blockquote style="color: #FFFFFF;">518</p>
</th>
<th>
<blockquote style="color: #FFFFFF;">4,37</p>
</th>
<th>
<blockquote style="color: #FFFFFF;">515</p>
</th>

</tr>
<tr>
<th>
<a href="https://drive.google.com/file/d/1QvbNt77hkL1Zsm-h9oi-xdBQ5Xa_AftU/view?usp=sharing"
target="_blank" style="color: #FFFFFF;">
<blockquote style="color: #FFFFFF;">Porá</p></img>
</a>
</th>
<th>
<blockquote style="color: #FFFFFF;">Lanús</p>
</th>

<th>
<blockquote style="color: #FFFFFF;">1355</p>
</th>
<th>
<blockquote style="color: #FFFFFF;">338</p>
</th>
<th>
<blockquote style="color: #FFFFFF;">324</p>
</th>
<th>
<blockquote style="color: #FFFFFF;">3,36</p>
</th>
<th>
<blockquote style="color: #FFFFFF;">403</p>
</th>
</tr>
<tr>
<th>
<blockquote style="color: #FFFFFF;">Campo Tongui</p>
</th>
<th>
<blockquote style="color: #FFFFFF;">Lomas de Zamora</p>
</th>
<th>
<blockquote style="color: #FFFFFF;">12834</p>
</th>
<th>
<blockquote style="color: #FFFFFF;">4087</p>
</th>
<th>
<blockquote style="color: #FFFFFF;">3998</p>
</th>
<th>
<blockquote style="color: #FFFFFF;">115,12</p>
</th>
<th>
<blockquote style="color: #FFFFFF;">111</p>
</th>
</tr>
<tr>
<th>
<blockquote style="color: #FFFFFF;">La Olla</p>
</th>
<th>
<blockquote style="color: #FFFFFF;">Malvinas Argentinas</p>
</th>
<th>
<blockquote style="color: #FFFFFF;">274</p>
</th>
<th>
<blockquote style="color: #FFFFFF;">72</p>
</th>
<th>
<blockquote style="color: #FFFFFF;">56</p>
</th>
<th>
<blockquote style="color: #FFFFFF;">1,79</p>
</th>
<th>
<blockquote style="color: #FFFFFF;">153</p>
</th>
</tr>
<tr>
<th>
<blockquote style="color: #FFFFFF;">Santa Elena</p>
</th>
<th>
<blockquote style="color: #FFFFFF;">Malvinas Argentinas</p>
</th>
<th>
<blockquote style="color: #FFFFFF;">264</p>
</th>
<th>
<blockquote style="color: #FFFFFF;">63</p>
</th>
<th>
<blockquote style="color: #FFFFFF;">61</p>
</th>
<th>
<blockquote style="color: #FFFFFF;">2,1</p>
</th>
<th>
<blockquote style="color: #FFFFFF;">126</p>
</th>
</tr>
<tr>
<th>
<a href="https://drive.google.com/file/d/1Vs2AVjArSy9dICUlkdeYf3_uK4BaMlrM/view?usp=sharing"
target="_blank" style="color: #FFFFFF;">
<blockquote style="color: #FFFFFF;">C.G -Pte. Sarmiento</p></img>
</a>
</th>
<th>
<blockquote style="color: #FFFFFF;">Morón</p>
</th>
<th>
<blockquote style="color: #FFFFFF;">4249</p>
</th>
<th>
<blockquote style="color: #FFFFFF;">1105</p>
</th>
<th>
<blockquote style="color: #FFFFFF;">1433</p>
</th>
<th>
<blockquote style="color: #FFFFFF;">12,2</p>
</th>
<th>
<blockquote style="color: #FFFFFF;">348</p>
</th>
</tr>
<tr>
<th>
<a href="https://drive.google.com/file/d/1Vs2AVjArSy9dICUlkdeYf3_uK4BaMlrM/view?usp=sharing"
target="_blank" style="color: #FFFFFF;">
<blockquote style="color: #FFFFFF;">C.G- Plan Federal</p></img>
</a>
</th>
<th>
<blockquote style="color: #FFFFFF;">Morón</p>
</th>

<th>
<blockquote style="color: #FFFFFF;">1566</p>
</th>
<th>
<blockquote style="color: #FFFFFF;">331</p>
</th>
<th>
<blockquote style="color: #FFFFFF;">574</p>
</th>
<th>
<blockquote style="color: #FFFFFF;">11,97</p>
</th>
<th>
<blockquote style="color: #FFFFFF;">130</p>
</th>
</tr>
<tr>
<th>
<a href="https://drive.google.com/file/d/1i341vFmaJIokZxD-ERa8QNLJKXXzQ1Bf/view?usp=sharing"
target="_blank" style="color: #FFFFFF;">
<blockquote style="color: #FFFFFF;">Monterrey</p></img>
</a>
</th>
<th>
<blockquote style="color: #FFFFFF;">Pilar</p>
</th>
<th>
<blockquote style="color: #FFFFFF;">13055</p>
</th>
<th>
<blockquote style="color: #FFFFFF;">3445</p>
</th>
<th>
<blockquote style="color: #FFFFFF;">3236</p>
</th>
<th>
<blockquote style="color: #FFFFFF;">134,73</p>
</th>
<th>
<blockquote style="color: #FFFFFF;">97</p>
</th>
</tr>
<tr>
<th>
<a href="https://drive.google.com/file/d/1eKWxCDr06lshg2T4QZGuKSSCYRXLwc9O/view?usp=sharing"
target="_blank" style="color: #FFFFFF;">
<blockquote style="color: #FFFFFF;">Itatí</p></img>
</a>
</th>
<th>
<blockquote style="color: #FFFFFF;">Quilmes</p>
</th>

<th>
<blockquote style="color: #FFFFFF;">15142</p>
</th>
<th>
<blockquote style="color: #FFFFFF;">4262</p>
</th>
<th>
<blockquote style="color: #FFFFFF;">4151</p>
</th>
<th>
<blockquote style="color: #FFFFFF;">50,85</p>
</th>
<th>
<blockquote style="color: #FFFFFF;">298</p>
</th>
</tr>
<tr>
<th>
<a href="https://drive.google.com/file/d/1eKWxCDr06lshg2T4QZGuKSSCYRXLwc9O/view?usp=sharing"
target="_blank" style="color: #FFFFFF;">
<blockquote style="color: #FFFFFF;">Azul</p></img>
</a>
</th>
<th>
<blockquote style="color: #FFFFFF;">Quilmes</p>
</th>
<th>
<blockquote style="color: #FFFFFF;">3128</p>
</th>
<th>
<blockquote style="color: #FFFFFF;">836</p>
</th>
<th>
<blockquote style="color: #FFFFFF;">799</p>
</th>
<th>
<blockquote style="color: #FFFFFF;">8,46</p>
</th>
<th>
<blockquote style="color: #FFFFFF;">370</p>
</th>
</tr>
<tr>
<th>
<a href="https://drive.google.com/file/d/1GwgOxmkaI__o85u4Qc38rmgOmKSrbZvM/view?usp=sharing"
target="_blank" style="color: #FFFFFF;">
<blockquote style="color: #FFFFFF;">La Cava</p></img>
</a>
</th>
<th>
<blockquote style="color: #FFFFFF;">San Isidro</p>
</th>
<th>
<blockquote style="color: #FFFFFF;">13515</p>
</th>
<th>
<blockquote style="color: #FFFFFF;">3475</p>
</th>
<th>
<blockquote style="color: #FFFFFF;">2426</p>
</th>
<th>
<blockquote style="color: #FFFFFF;">18,21</p>
</th>
<th>
<blockquote style="color: #FFFFFF;">742</p>
</th>
</tr>
<tr>
<th>
<a href="https://drive.google.com/file/d/1vXTgeefEqODJ4Q4q-Hdyq2Sd65IXomjq/view?usp=sharing"
target="_blank" style="color: #FFFFFF;">
<blockquote style="color: #FFFFFF;">Biocca</p></img>
</a>
</th>
<th>
<blockquote style="color: #FFFFFF;">San Vicente</p>
</th>
<th>
<blockquote style="color: #FFFFFF;">1714</p>
</th>
<th>
<blockquote style="color: #FFFFFF;">464</p>
</th>
<th>
<blockquote style="color: #FFFFFF;">489</p>
</th>
<th>
<blockquote style="color: #FFFFFF;">47,99</p>
</th>
<th>
<blockquote style="color: #FFFFFF;">36</p>
</th>
</tr>
<!--th>
<a href="https://drive.google.com/file/d/1vXTgeefEqODJ4Q4q-Hdyq2Sd65IXomjq/view?usp=sharing" target="_blank"><blockquote style="color: #FFFFFF;" >San Jose FFCC</p></img></a>
</th>
<th><blockquote style="color: #FFFFFF;">San Vicente</p></th>
<th><blockquote style="color: #FFFFFF;">241</p></th>
<th><blockquote style="color: #FFFFFF;">65</p></th>
<th><blockquote style="color: #FFFFFF;">69</p></th>
<th><blockquote style="color: #FFFFFF;">6,97</p></th>
<th><blockquote style="color: #FFFFFF;">35</p></th>
</tr-->
<tr>
<th>
<a href="https://drive.google.com/file/d/1vXTgeefEqODJ4Q4q-Hdyq2Sd65IXomjq/view?usp=sharing"
target="_blank" style="color: #FFFFFF;">
<blockquote style="color: #FFFFFF;">San Jose </p></img>
</a>
</th>
<th>
<blockquote style="color: #FFFFFF;">San Vicente</p>
</th>
<th>
<blockquote style="color: #FFFFFF;">3069</p>
</th>
<th>
<blockquote style="color: #FFFFFF;">812</p>
</th>
<th>
<blockquote style="color: #FFFFFF;">884</p>
</th>
<th>
<blockquote style="color: #FFFFFF;">81,92</p>
</th>
<th>
<blockquote style="color: #FFFFFF;">37</p>
</th>
</tr>
<tr>
<th>
<a href="https://drive.google.com/file/d/1u7iWXwINU1ex6rBbnCWpMd4gakGTqyL-/view?usp=sharing"
target="_blank" style="color: #FFFFFF;">
<blockquote style="color: #FFFFFF;">Garrote</p></img>
</a>
</th>
<th>
<blockquote style="color: #FFFFFF;">Tigre</p>
</th>
<th>
<blockquote style="color: #FFFFFF;">2649</p>
</th>
<th>
<blockquote style="color: #FFFFFF;">790</p>
</th>
<th>
<blockquote style="color: #FFFFFF;">806</p>
</th>
<th>
<blockquote style="color: #FFFFFF;">12,90</p>
</th>
<th>
<blockquote style="color: #FFFFFF;">205</p>
</th>
</tr>
<tr>
<th>
<blockquote style="color: #FFFFFF;">Esperanza</p>
</th>
<th>
<blockquote style="color: #FFFFFF;">Tres de Febrero</p>
</th>
<th>
<blockquote style="color: #FFFFFF;">755</p>
</th>
<th>
<blockquote style="color: #FFFFFF;">182</p>
</th>
<th>
<blockquote style="color: #FFFFFF;">148</p>
</th>
<th>
<blockquote style="color: #FFFFFF;">4,51</p>
</th>
<th>
<blockquote style="color: #FFFFFF;">167</p>
</th>
</tr>
<tr>

<th>
<blockquote style="color: #FFFFFF;"></p>
</th>
<th><h3 style="color: #FFFFFF;">TOTAL</p></th>

<th>
<blockquote style="color: #FFFFFF;">136.473</p>
</th>
<th>
<blockquote style="color: #FFFFFF;">37.152</p>
</th>
<th>
<blockquote style="color: #FFFFFF;">35.248</p>
</th>
<th>
<blockquote style="color: #FFFFFF;">951,83</p>
</th>
<th>
<blockquote style="color: #FFFFFF;">202 (promedio)</p>
</th>
</tr>

</tbody>
